gimmebio.entropy_scores-0.5.6-py3.6-nspkg.pth
gimmebio/entropy_scores/__init__.py
gimmebio/entropy_scores/cli.py
gimmebio/entropy_scores/entropy_scores.py
gimmebio.entropy_scores-0.5.6.dist-info/METADATA
gimmebio.entropy_scores-0.5.6.dist-info/RECORD
gimmebio.entropy_scores-0.5.6.dist-info/WHEEL
gimmebio.entropy_scores-0.5.6.dist-info/namespace_packages.txt
gimmebio.entropy_scores-0.5.6.dist-info/top_level.txt
